{
  "id": "6188d76b-cf34-4939-bd38-58d45634a689",
  "prevId": "00000000-0000-0000-0000-000000000000",
  "version": "7",
  "dialect": "postgresql",
  "tables": {
    "public.audit_logs": {
      "name": "audit_logs",
      "schema": "",
      "columns": {
        "id": {
          "name": "id",
          "type": "serial",
          "primaryKey": true,
          "notNull": true
        },
        "user_id": {
          "name": "user_id",
          "type": "varchar(36)",
          "primaryKey": false,
          "notNull": false
        },
        "action": {
          "name": "action",
          "type": "text",
          "primaryKey": false,
          "notNull": true
        },
        "entity_type": {
          "name": "entity_type",
          "type": "text",
          "primaryKey": false,
          "notNull": true
        },
        "entity_id": {
          "name": "entity_id",
          "type": "text",
          "primaryKey": false,
          "notNull": false
        },
        "payload": {
          "name": "payload",
          "type": "jsonb",
          "primaryKey": false,
          "notNull": false
        },
        "ip_address": {
          "name": "ip_address",
          "type": "text",
          "primaryKey": false,
          "notNull": false
        },
        "created_at": {
          "name": "created_at",
          "type": "timestamp",
          "primaryKey": false,
          "notNull": true,
          "default": "now()"
        }
      },
      "indexes": {
        "audit_logs_user_idx": {
          "name": "audit_logs_user_idx",
          "columns": [
            {
              "expression": "user_id",
              "isExpression": false,
              "asc": true,
              "nulls": "last"
            }
          ],
          "isUnique": false,
          "concurrently": false,
          "method": "btree",
          "with": {}
        },
        "audit_logs_entity_idx": {
          "name": "audit_logs_entity_idx",
          "columns": [
            {
              "expression": "entity_type",
              "isExpression": false,
              "asc": true,
              "nulls": "last"
            },
            {
              "expression": "entity_id",
              "isExpression": false,
              "asc": true,
              "nulls": "last"
            }
          ],
          "isUnique": false,
          "concurrently": false,
          "method": "btree",
          "with": {}
        },
        "audit_logs_action_idx": {
          "name": "audit_logs_action_idx",
          "columns": [
            {
              "expression": "action",
              "isExpression": false,
              "asc": true,
              "nulls": "last"
            }
          ],
          "isUnique": false,
          "concurrently": false,
          "method": "btree",
          "with": {}
        },
        "audit_logs_created_idx": {
          "name": "audit_logs_created_idx",
          "columns": [
            {
              "expression": "created_at",
              "isExpression": false,
              "asc": true,
              "nulls": "last"
            }
          ],
          "isUnique": false,
          "concurrently": false,
          "method": "btree",
          "with": {}
        }
      },
      "foreignKeys": {
        "audit_logs_user_id_users_id_fk": {
          "name": "audit_logs_user_id_users_id_fk",
          "tableFrom": "audit_logs",
          "tableTo": "users",
          "columnsFrom": [
            "user_id"
          ],
          "columnsTo": [
            "id"
          ],
          "onDelete": "set null",
          "onUpdate": "no action"
        }
      },
      "compositePrimaryKeys": {},
      "uniqueConstraints": {},
      "policies": {},
      "checkConstraints": {},
      "isRLSEnabled": false
    },
    "public.departments": {
      "name": "departments",
      "schema": "",
      "columns": {
        "id": {
          "name": "id",
          "type": "varchar(50)",
          "primaryKey": true,
          "notNull": true
        },
        "label": {
          "name": "label",
          "type": "text",
          "primaryKey": false,
          "notNull": true
        },
        "description": {
          "name": "description",
          "type": "text",
          "primaryKey": false,
          "notNull": false
        },
        "created_at": {
          "name": "created_at",
          "type": "timestamp",
          "primaryKey": false,
          "notNull": true,
          "default": "now()"
        },
        "updated_at": {
          "name": "updated_at",
          "type": "timestamp",
          "primaryKey": false,
          "notNull": true,
          "default": "now()"
        }
      },
      "indexes": {},
      "foreignKeys": {},
      "compositePrimaryKeys": {},
      "uniqueConstraints": {},
      "policies": {},
      "checkConstraints": {},
      "isRLSEnabled": false
    },
    "public.document_templates": {
      "name": "document_templates",
      "schema": "",
      "columns": {
        "id": {
          "name": "id",
          "type": "varchar(36)",
          "primaryKey": true,
          "notNull": true,
          "default": "gen_random_uuid()"
        },
        "template_type": {
          "name": "template_type",
          "type": "text",
          "primaryKey": false,
          "notNull": true
        },
        "document_type": {
          "name": "document_type",
          "type": "text",
          "primaryKey": false,
          "notNull": true
        },
        "google_docs_link": {
          "name": "google_docs_link",
          "type": "text",
          "primaryKey": false,
          "notNull": false
        },
        "created_at": {
          "name": "created_at",
          "type": "timestamp",
          "primaryKey": false,
          "notNull": true,
          "default": "now()"
        },
        "updated_at": {
          "name": "updated_at",
          "type": "timestamp",
          "primaryKey": false,
          "notNull": true,
          "default": "now()"
        }
      },
      "indexes": {},
      "foreignKeys": {},
      "compositePrimaryKeys": {},
      "uniqueConstraints": {},
      "policies": {},
      "checkConstraints": {},
      "isRLSEnabled": false
    },
    "public.employees": {
      "name": "employees",
      "schema": "",
      "columns": {
        "id": {
          "name": "id",
          "type": "serial",
          "primaryKey": true,
          "notNull": true
        },
        "employee_code": {
          "name": "employee_code",
          "type": "varchar(20)",
          "primaryKey": false,
          "notNull": true
        },
        "user_id": {
          "name": "user_id",
          "type": "varchar(36)",
          "primaryKey": false,
          "notNull": false
        },
        "email": {
          "name": "email",
          "type": "text",
          "primaryKey": false,
          "notNull": true
        },
        "first_name": {
          "name": "first_name",
          "type": "text",
          "primaryKey": false,
          "notNull": true
        },
        "last_name": {
          "name": "last_name",
          "type": "text",
          "primaryKey": false,
          "notNull": true
        },
        "full_name": {
          "name": "full_name",
          "type": "text",
          "primaryKey": false,
          "notNull": true
        },
        "department_id": {
          "name": "department_id",
          "type": "varchar(50)",
          "primaryKey": false,
          "notNull": false
        },
        "position": {
          "name": "position",
          "type": "text",
          "primaryKey": false,
          "notNull": false
        },
        "manager_employee_id": {
          "name": "manager_employee_id",
          "type": "integer",
          "primaryKey": false,
          "notNull": false
        },
        "status": {
          "name": "status",
          "type": "text",
          "primaryKey": false,
          "notNull": true,
          "default": "'active'"
        },
        "hire_date": {
          "name": "hire_date",
          "type": "date",
          "primaryKey": false,
          "notNull": false
        },
        "termination_date": {
          "name": "termination_date",
          "type": "date",
          "primaryKey": false,
          "notNull": false
        },
        "created_at": {
          "name": "created_at",
          "type": "timestamp",
          "primaryKey": false,
          "notNull": true,
          "default": "now()"
        },
        "updated_at": {
          "name": "updated_at",
          "type": "timestamp",
          "primaryKey": false,
          "notNull": true,
          "default": "now()"
        }
      },
      "indexes": {
        "employees_user_id_idx": {
          "name": "employees_user_id_idx",
          "columns": [
            {
              "expression": "user_id",
              "isExpression": false,
              "asc": true,
              "nulls": "last"
            }
          ],
          "isUnique": false,
          "concurrently": false,
          "method": "btree",
          "with": {}
        },
        "employees_department_idx": {
          "name": "employees_department_idx",
          "columns": [
            {
              "expression": "department_id",
              "isExpression": false,
              "asc": true,
              "nulls": "last"
            }
          ],
          "isUnique": false,
          "concurrently": false,
          "method": "btree",
          "with": {}
        },
        "employees_manager_idx": {
          "name": "employees_manager_idx",
          "columns": [
            {
              "expression": "manager_employee_id",
              "isExpression": false,
              "asc": true,
              "nulls": "last"
            }
          ],
          "isUnique": false,
          "concurrently": false,
          "method": "btree",
          "with": {}
        },
        "employees_status_idx": {
          "name": "employees_status_idx",
          "columns": [
            {
              "expression": "status",
              "isExpression": false,
              "asc": true,
              "nulls": "last"
            }
          ],
          "isUnique": false,
          "concurrently": false,
          "method": "btree",
          "with": {}
        },
        "employees_email_idx": {
          "name": "employees_email_idx",
          "columns": [
            {
              "expression": "email",
              "isExpression": false,
              "asc": true,
              "nulls": "last"
            }
          ],
          "isUnique": false,
          "concurrently": false,
          "method": "btree",
          "with": {}
        }
      },
      "foreignKeys": {
        "employees_user_id_users_id_fk": {
          "name": "employees_user_id_users_id_fk",
          "tableFrom": "employees",
          "tableTo": "users",
          "columnsFrom": [
            "user_id"
          ],
          "columnsTo": [
            "id"
          ],
          "onDelete": "set null",
          "onUpdate": "no action"
        },
        "employees_manager_employee_id_employees_id_fk": {
          "name": "employees_manager_employee_id_employees_id_fk",
          "tableFrom": "employees",
          "tableTo": "employees",
          "columnsFrom": [
            "manager_employee_id"
          ],
          "columnsTo": [
            "id"
          ],
          "onDelete": "set null",
          "onUpdate": "no action"
        }
      },
      "compositePrimaryKeys": {},
      "uniqueConstraints": {
        "employees_employee_code_unique": {
          "name": "employees_employee_code_unique",
          "nullsNotDistinct": false,
          "columns": [
            "employee_code"
          ]
        },
        "employees_user_id_unique": {
          "name": "employees_user_id_unique",
          "nullsNotDistinct": false,
          "columns": [
            "user_id"
          ]
        },
        "employees_email_unique": {
          "name": "employees_email_unique",
          "nullsNotDistinct": false,
          "columns": [
            "email"
          ]
        }
      },
      "policies": {},
      "checkConstraints": {},
      "isRLSEnabled": false
    },
    "public.feedback": {
      "name": "feedback",
      "schema": "",
      "columns": {
        "id": {
          "name": "id",
          "type": "serial",
          "primaryKey": true,
          "notNull": true
        },
        "giver_employee_id": {
          "name": "giver_employee_id",
          "type": "integer",
          "primaryKey": false,
          "notNull": false
        },
        "receiver_employee_id": {
          "name": "receiver_employee_id",
          "type": "integer",
          "primaryKey": false,
          "notNull": true
        },
        "cycle_id": {
          "name": "cycle_id",
          "type": "integer",
          "primaryKey": false,
          "notNull": false
        },
        "is_anonymous": {
          "name": "is_anonymous",
          "type": "boolean",
          "primaryKey": false,
          "notNull": true,
          "default": false
        },
        "content": {
          "name": "content",
          "type": "text",
          "primaryKey": false,
          "notNull": true
        },
        "category": {
          "name": "category",
          "type": "text",
          "primaryKey": false,
          "notNull": false
        },
        "created_at": {
          "name": "created_at",
          "type": "timestamp",
          "primaryKey": false,
          "notNull": true,
          "default": "now()"
        }
      },
      "indexes": {
        "feedback_receiver_idx": {
          "name": "feedback_receiver_idx",
          "columns": [
            {
              "expression": "receiver_employee_id",
              "isExpression": false,
              "asc": true,
              "nulls": "last"
            }
          ],
          "isUnique": false,
          "concurrently": false,
          "method": "btree",
          "with": {}
        },
        "feedback_giver_idx": {
          "name": "feedback_giver_idx",
          "columns": [
            {
              "expression": "giver_employee_id",
              "isExpression": false,
              "asc": true,
              "nulls": "last"
            }
          ],
          "isUnique": false,
          "concurrently": false,
          "method": "btree",
          "with": {}
        },
        "feedback_cycle_idx": {
          "name": "feedback_cycle_idx",
          "columns": [
            {
              "expression": "cycle_id",
              "isExpression": false,
              "asc": true,
              "nulls": "last"
            }
          ],
          "isUnique": false,
          "concurrently": false,
          "method": "btree",
          "with": {}
        }
      },
      "foreignKeys": {
        "feedback_giver_employee_id_employees_id_fk": {
          "name": "feedback_giver_employee_id_employees_id_fk",
          "tableFrom": "feedback",
          "tableTo": "employees",
          "columnsFrom": [
            "giver_employee_id"
          ],
          "columnsTo": [
            "id"
          ],
          "onDelete": "set null",
          "onUpdate": "no action"
        },
        "feedback_receiver_employee_id_employees_id_fk": {
          "name": "feedback_receiver_employee_id_employees_id_fk",
          "tableFrom": "feedback",
          "tableTo": "employees",
          "columnsFrom": [
            "receiver_employee_id"
          ],
          "columnsTo": [
            "id"
          ],
          "onDelete": "cascade",
          "onUpdate": "no action"
        },
        "feedback_cycle_id_review_cycles_id_fk": {
          "name": "feedback_cycle_id_review_cycles_id_fk",
          "tableFrom": "feedback",
          "tableTo": "review_cycles",
          "columnsFrom": [
            "cycle_id"
          ],
          "columnsTo": [
            "id"
          ],
          "onDelete": "set null",
          "onUpdate": "no action"
        }
      },
      "compositePrimaryKeys": {},
      "uniqueConstraints": {},
      "policies": {},
      "checkConstraints": {},
      "isRLSEnabled": false
    },
    "public.goal_updates": {
      "name": "goal_updates",
      "schema": "",
      "columns": {
        "id": {
          "name": "id",
          "type": "serial",
          "primaryKey": true,
          "notNull": true
        },
        "goal_id": {
          "name": "goal_id",
          "type": "integer",
          "primaryKey": false,
          "notNull": true
        },
        "progress": {
          "name": "progress",
          "type": "numeric(5, 2)",
          "primaryKey": false,
          "notNull": false
        },
        "comment": {
          "name": "comment",
          "type": "text",
          "primaryKey": false,
          "notNull": false
        },
        "created_by": {
          "name": "created_by",
          "type": "varchar(36)",
          "primaryKey": false,
          "notNull": false
        },
        "created_at": {
          "name": "created_at",
          "type": "timestamp",
          "primaryKey": false,
          "notNull": true,
          "default": "now()"
        }
      },
      "indexes": {
        "goal_updates_goal_idx": {
          "name": "goal_updates_goal_idx",
          "columns": [
            {
              "expression": "goal_id",
              "isExpression": false,
              "asc": true,
              "nulls": "last"
            }
          ],
          "isUnique": false,
          "concurrently": false,
          "method": "btree",
          "with": {}
        }
      },
      "foreignKeys": {
        "goal_updates_goal_id_goals_id_fk": {
          "name": "goal_updates_goal_id_goals_id_fk",
          "tableFrom": "goal_updates",
          "tableTo": "goals",
          "columnsFrom": [
            "goal_id"
          ],
          "columnsTo": [
            "id"
          ],
          "onDelete": "cascade",
          "onUpdate": "no action"
        },
        "goal_updates_created_by_users_id_fk": {
          "name": "goal_updates_created_by_users_id_fk",
          "tableFrom": "goal_updates",
          "tableTo": "users",
          "columnsFrom": [
            "created_by"
          ],
          "columnsTo": [
            "id"
          ],
          "onDelete": "no action",
          "onUpdate": "no action"
        }
      },
      "compositePrimaryKeys": {},
      "uniqueConstraints": {},
      "policies": {},
      "checkConstraints": {},
      "isRLSEnabled": false
    },
    "public.goals": {
      "name": "goals",
      "schema": "",
      "columns": {
        "id": {
          "name": "id",
          "type": "serial",
          "primaryKey": true,
          "notNull": true
        },
        "employee_id": {
          "name": "employee_id",
          "type": "integer",
          "primaryKey": false,
          "notNull": true
        },
        "cycle_id": {
          "name": "cycle_id",
          "type": "integer",
          "primaryKey": false,
          "notNull": false
        },
        "title": {
          "name": "title",
          "type": "text",
          "primaryKey": false,
          "notNull": true
        },
        "description": {
          "name": "description",
          "type": "text",
          "primaryKey": false,
          "notNull": false
        },
        "status": {
          "name": "status",
          "type": "text",
          "primaryKey": false,
          "notNull": true,
          "default": "'not_started'"
        },
        "weight": {
          "name": "weight",
          "type": "numeric(5, 2)",
          "primaryKey": false,
          "notNull": false
        },
        "start_date": {
          "name": "start_date",
          "type": "date",
          "primaryKey": false,
          "notNull": false
        },
        "due_date": {
          "name": "due_date",
          "type": "date",
          "primaryKey": false,
          "notNull": false
        },
        "completed_at": {
          "name": "completed_at",
          "type": "timestamp",
          "primaryKey": false,
          "notNull": false
        },
        "visibility": {
          "name": "visibility",
          "type": "text",
          "primaryKey": false,
          "notNull": true,
          "default": "'private'"
        },
        "created_at": {
          "name": "created_at",
          "type": "timestamp",
          "primaryKey": false,
          "notNull": true,
          "default": "now()"
        },
        "updated_at": {
          "name": "updated_at",
          "type": "timestamp",
          "primaryKey": false,
          "notNull": true,
          "default": "now()"
        }
      },
      "indexes": {
        "goals_employee_idx": {
          "name": "goals_employee_idx",
          "columns": [
            {
              "expression": "employee_id",
              "isExpression": false,
              "asc": true,
              "nulls": "last"
            }
          ],
          "isUnique": false,
          "concurrently": false,
          "method": "btree",
          "with": {}
        },
        "goals_cycle_idx": {
          "name": "goals_cycle_idx",
          "columns": [
            {
              "expression": "cycle_id",
              "isExpression": false,
              "asc": true,
              "nulls": "last"
            }
          ],
          "isUnique": false,
          "concurrently": false,
          "method": "btree",
          "with": {}
        },
        "goals_status_idx": {
          "name": "goals_status_idx",
          "columns": [
            {
              "expression": "status",
              "isExpression": false,
              "asc": true,
              "nulls": "last"
            }
          ],
          "isUnique": false,
          "concurrently": false,
          "method": "btree",
          "with": {}
        }
      },
      "foreignKeys": {
        "goals_employee_id_employees_id_fk": {
          "name": "goals_employee_id_employees_id_fk",
          "tableFrom": "goals",
          "tableTo": "employees",
          "columnsFrom": [
            "employee_id"
          ],
          "columnsTo": [
            "id"
          ],
          "onDelete": "cascade",
          "onUpdate": "no action"
        },
        "goals_cycle_id_review_cycles_id_fk": {
          "name": "goals_cycle_id_review_cycles_id_fk",
          "tableFrom": "goals",
          "tableTo": "review_cycles",
          "columnsFrom": [
            "cycle_id"
          ],
          "columnsTo": [
            "id"
          ],
          "onDelete": "set null",
          "onUpdate": "no action"
        }
      },
      "compositePrimaryKeys": {},
      "uniqueConstraints": {},
      "policies": {},
      "checkConstraints": {},
      "isRLSEnabled": false
    },
    "public.invitations": {
      "name": "invitations",
      "schema": "",
      "columns": {
        "id": {
          "name": "id",
          "type": "varchar(36)",
          "primaryKey": true,
          "notNull": true,
          "default": "gen_random_uuid()"
        },
        "email": {
          "name": "email",
          "type": "text",
          "primaryKey": false,
          "notNull": true
        },
        "first_name": {
          "name": "first_name",
          "type": "text",
          "primaryKey": false,
          "notNull": true
        },
        "last_name": {
          "name": "last_name",
          "type": "text",
          "primaryKey": false,
          "notNull": true
        },
        "token": {
          "name": "token",
          "type": "text",
          "primaryKey": false,
          "notNull": true
        },
        "position": {
          "name": "position",
          "type": "text",
          "primaryKey": false,
          "notNull": true
        },
        "department": {
          "name": "department",
          "type": "text",
          "primaryKey": false,
          "notNull": true
        },
        "probation_months": {
          "name": "probation_months",
          "type": "text",
          "primaryKey": false,
          "notNull": false
        },
        "notice_months": {
          "name": "notice_months",
          "type": "text",
          "primaryKey": false,
          "notNull": false
        },
        "start_date": {
          "name": "start_date",
          "type": "date",
          "primaryKey": false,
          "notNull": false
        },
        "salary": {
          "name": "salary",
          "type": "numeric(10, 2)",
          "primaryKey": false,
          "notNull": true
        },
        "equity_shares": {
          "name": "equity_shares",
          "type": "text",
          "primaryKey": false,
          "notNull": false
        },
        "vesting_years": {
          "name": "vesting_years",
          "type": "text",
          "primaryKey": false,
          "notNull": false
        },
        "cliff_years": {
          "name": "cliff_years",
          "type": "text",
          "primaryKey": false,
          "notNull": false
        },
        "vacation_days": {
          "name": "vacation_days",
          "type": "text",
          "primaryKey": false,
          "notNull": false
        },
        "remote_vacation_days": {
          "name": "remote_vacation_days",
          "type": "text",
          "primaryKey": false,
          "notNull": false
        },
        "message": {
          "name": "message",
          "type": "text",
          "primaryKey": false,
          "notNull": false
        },
        "is_used": {
          "name": "is_used",
          "type": "boolean",
          "primaryKey": false,
          "notNull": true,
          "default": false
        },
        "created_at": {
          "name": "created_at",
          "type": "timestamp",
          "primaryKey": false,
          "notNull": true,
          "default": "now()"
        },
        "used_at": {
          "name": "used_at",
          "type": "timestamp",
          "primaryKey": false,
          "notNull": false
        }
      },
      "indexes": {},
      "foreignKeys": {},
      "compositePrimaryKeys": {},
      "uniqueConstraints": {
        "invitations_token_unique": {
          "name": "invitations_token_unique",
          "nullsNotDistinct": false,
          "columns": [
            "token"
          ]
        }
      },
      "policies": {},
      "checkConstraints": {},
      "isRLSEnabled": false
    },
    "public.new_joiners": {
      "name": "new_joiners",
      "schema": "",
      "columns": {
        "id": {
          "name": "id",
          "type": "varchar(36)",
          "primaryKey": true,
          "notNull": true,
          "default": "gen_random_uuid()"
        },
        "invitation_id": {
          "name": "invitation_id",
          "type": "varchar(36)",
          "primaryKey": false,
          "notNull": false
        },
        "first_name": {
          "name": "first_name",
          "type": "text",
          "primaryKey": false,
          "notNull": true
        },
        "last_name": {
          "name": "last_name",
          "type": "text",
          "primaryKey": false,
          "notNull": true
        },
        "email": {
          "name": "email",
          "type": "text",
          "primaryKey": false,
          "notNull": true
        },
        "phone": {
          "name": "phone",
          "type": "text",
          "primaryKey": false,
          "notNull": true
        },
        "address": {
          "name": "address",
          "type": "text",
          "primaryKey": false,
          "notNull": true
        },
        "position": {
          "name": "position",
          "type": "text",
          "primaryKey": false,
          "notNull": true
        },
        "department": {
          "name": "department",
          "type": "text",
          "primaryKey": false,
          "notNull": true
        },
        "probation_months": {
          "name": "probation_months",
          "type": "text",
          "primaryKey": false,
          "notNull": false
        },
        "notice_months": {
          "name": "notice_months",
          "type": "text",
          "primaryKey": false,
          "notNull": false
        },
        "start_date": {
          "name": "start_date",
          "type": "date",
          "primaryKey": false,
          "notNull": true
        },
        "salary": {
          "name": "salary",
          "type": "numeric(10, 2)",
          "primaryKey": false,
          "notNull": true
        },
        "equity_shares": {
          "name": "equity_shares",
          "type": "text",
          "primaryKey": false,
          "notNull": false
        },
        "vesting_years": {
          "name": "vesting_years",
          "type": "text",
          "primaryKey": false,
          "notNull": false
        },
        "cliff_years": {
          "name": "cliff_years",
          "type": "text",
          "primaryKey": false,
          "notNull": false
        },
        "vacation_days": {
          "name": "vacation_days",
          "type": "text",
          "primaryKey": false,
          "notNull": false
        },
        "remote_vacation_days": {
          "name": "remote_vacation_days",
          "type": "text",
          "primaryKey": false,
          "notNull": false
        },
        "offer_letter_status": {
          "name": "offer_letter_status",
          "type": "text",
          "primaryKey": false,
          "notNull": true,
          "default": "'pending'"
        },
        "contract_status": {
          "name": "contract_status",
          "type": "text",
          "primaryKey": false,
          "notNull": true,
          "default": "'pending'"
        },
        "esop_status": {
          "name": "esop_status",
          "type": "text",
          "primaryKey": false,
          "notNull": true,
          "default": "'pending'"
        },
        "docusign_envelope_id": {
          "name": "docusign_envelope_id",
          "type": "text",
          "primaryKey": false,
          "notNull": false
        },
        "created_at": {
          "name": "created_at",
          "type": "timestamp",
          "primaryKey": false,
          "notNull": true,
          "default": "now()"
        }
      },
      "indexes": {},
      "foreignKeys": {
        "new_joiners_invitation_id_invitations_id_fk": {
          "name": "new_joiners_invitation_id_invitations_id_fk",
          "tableFrom": "new_joiners",
          "tableTo": "invitations",
          "columnsFrom": [
            "invitation_id"
          ],
          "columnsTo": [
            "id"
          ],
          "onDelete": "no action",
          "onUpdate": "no action"
        }
      },
      "compositePrimaryKeys": {},
      "uniqueConstraints": {},
      "policies": {},
      "checkConstraints": {},
      "isRLSEnabled": false
    },
    "public.reconciliation_results": {
      "name": "reconciliation_results",
      "schema": "",
      "columns": {
        "id": {
          "name": "id",
          "type": "serial",
          "primaryKey": true,
          "notNull": true
        },
        "run_id": {
          "name": "run_id",
          "type": "integer",
          "primaryKey": false,
          "notNull": true
        },
        "match_status": {
          "name": "match_status",
          "type": "text",
          "primaryKey": false,
          "notNull": true
        },
        "transaction_reference": {
          "name": "transaction_reference",
          "type": "text",
          "primaryKey": false,
          "notNull": true
        },
        "bank_data": {
          "name": "bank_data",
          "type": "jsonb",
          "primaryKey": false,
          "notNull": false
        },
        "database_data": {
          "name": "database_data",
          "type": "jsonb",
          "primaryKey": false,
          "notNull": false
        },
        "created_at": {
          "name": "created_at",
          "type": "timestamp",
          "primaryKey": false,
          "notNull": true,
          "default": "now()"
        }
      },
      "indexes": {
        "reconciliation_results_run_idx": {
          "name": "reconciliation_results_run_idx",
          "columns": [
            {
              "expression": "run_id",
              "isExpression": false,
              "asc": true,
              "nulls": "last"
            }
          ],
          "isUnique": false,
          "concurrently": false,
          "method": "btree",
          "with": {}
        },
        "reconciliation_results_status_idx": {
          "name": "reconciliation_results_status_idx",
          "columns": [
            {
              "expression": "match_status",
              "isExpression": false,
              "asc": true,
              "nulls": "last"
            }
          ],
          "isUnique": false,
          "concurrently": false,
          "method": "btree",
          "with": {}
        }
      },
      "foreignKeys": {
        "reconciliation_results_run_id_reconciliation_runs_id_fk": {
          "name": "reconciliation_results_run_id_reconciliation_runs_id_fk",
          "tableFrom": "reconciliation_results",
          "tableTo": "reconciliation_runs",
          "columnsFrom": [
            "run_id"
          ],
          "columnsTo": [
            "id"
          ],
          "onDelete": "cascade",
          "onUpdate": "no action"
        }
      },
      "compositePrimaryKeys": {},
      "uniqueConstraints": {},
      "policies": {},
      "checkConstraints": {},
      "isRLSEnabled": false
    },
    "public.reconciliation_runs": {
      "name": "reconciliation_runs",
      "schema": "",
      "columns": {
        "id": {
          "name": "id",
          "type": "serial",
          "primaryKey": true,
          "notNull": true
        },
        "bank_statement_filename": {
          "name": "bank_statement_filename",
          "type": "text",
          "primaryKey": false,
          "notNull": false
        },
        "database_filename": {
          "name": "database_filename",
          "type": "text",
          "primaryKey": false,
          "notNull": false
        },
        "value_date_filter": {
          "name": "value_date_filter",
          "type": "text",
          "primaryKey": false,
          "notNull": false
        },
        "total_matched": {
          "name": "total_matched",
          "type": "integer",
          "primaryKey": false,
          "notNull": true,
          "default": 0
        },
        "total_bank_only": {
          "name": "total_bank_only",
          "type": "integer",
          "primaryKey": false,
          "notNull": true,
          "default": 0
        },
        "total_database_only": {
          "name": "total_database_only",
          "type": "integer",
          "primaryKey": false,
          "notNull": true,
          "default": 0
        },
        "total_records": {
          "name": "total_records",
          "type": "integer",
          "primaryKey": false,
          "notNull": true,
          "default": 0
        },
        "total_bank_credit": {
          "name": "total_bank_credit",
          "type": "numeric(15, 2)",
          "primaryKey": false,
          "notNull": true,
          "default": "'0'"
        },
        "total_meta_base_amount": {
          "name": "total_meta_base_amount",
          "type": "numeric(15, 2)",
          "primaryKey": false,
          "notNull": true,
          "default": "'0'"
        },
        "total_deducted_amount": {
          "name": "total_deducted_amount",
          "type": "numeric(15, 2)",
          "primaryKey": false,
          "notNull": true,
          "default": "'0'"
        },
        "total_transaction_amount": {
          "name": "total_transaction_amount",
          "type": "numeric(15, 2)",
          "primaryKey": false,
          "notNull": true,
          "default": "'0'"
        },
        "checkout_aed": {
          "name": "checkout_aed",
          "type": "numeric(15, 2)",
          "primaryKey": false,
          "notNull": true,
          "default": "'0'"
        },
        "checkout_usd": {
          "name": "checkout_usd",
          "type": "numeric(15, 2)",
          "primaryKey": false,
          "notNull": true,
          "default": "'0'"
        },
        "tap_usd": {
          "name": "tap_usd",
          "type": "numeric(15, 2)",
          "primaryKey": false,
          "notNull": true,
          "default": "'0'"
        },
        "created_at": {
          "name": "created_at",
          "type": "timestamp",
          "primaryKey": false,
          "notNull": true,
          "default": "now()"
        }
      },
      "indexes": {
        "reconciliation_runs_created_idx": {
          "name": "reconciliation_runs_created_idx",
          "columns": [
            {
              "expression": "created_at",
              "isExpression": false,
              "asc": true,
              "nulls": "last"
            }
          ],
          "isUnique": false,
          "concurrently": false,
          "method": "btree",
          "with": {}
        }
      },
      "foreignKeys": {},
      "compositePrimaryKeys": {},
      "uniqueConstraints": {},
      "policies": {},
      "checkConstraints": {},
      "isRLSEnabled": false
    },
    "public.review_cycles": {
      "name": "review_cycles",
      "schema": "",
      "columns": {
        "id": {
          "name": "id",
          "type": "serial",
          "primaryKey": true,
          "notNull": true
        },
        "name": {
          "name": "name",
          "type": "text",
          "primaryKey": false,
          "notNull": true
        },
        "description": {
          "name": "description",
          "type": "text",
          "primaryKey": false,
          "notNull": false
        },
        "period_start": {
          "name": "period_start",
          "type": "date",
          "primaryKey": false,
          "notNull": true
        },
        "period_end": {
          "name": "period_end",
          "type": "date",
          "primaryKey": false,
          "notNull": true
        },
        "status": {
          "name": "status",
          "type": "text",
          "primaryKey": false,
          "notNull": true,
          "default": "'draft'"
        },
        "created_by": {
          "name": "created_by",
          "type": "varchar(36)",
          "primaryKey": false,
          "notNull": false
        },
        "created_at": {
          "name": "created_at",
          "type": "timestamp",
          "primaryKey": false,
          "notNull": true,
          "default": "now()"
        },
        "updated_at": {
          "name": "updated_at",
          "type": "timestamp",
          "primaryKey": false,
          "notNull": true,
          "default": "now()"
        }
      },
      "indexes": {
        "review_cycles_status_idx": {
          "name": "review_cycles_status_idx",
          "columns": [
            {
              "expression": "status",
              "isExpression": false,
              "asc": true,
              "nulls": "last"
            }
          ],
          "isUnique": false,
          "concurrently": false,
          "method": "btree",
          "with": {}
        },
        "review_cycles_period_idx": {
          "name": "review_cycles_period_idx",
          "columns": [
            {
              "expression": "period_start",
              "isExpression": false,
              "asc": true,
              "nulls": "last"
            },
            {
              "expression": "period_end",
              "isExpression": false,
              "asc": true,
              "nulls": "last"
            }
          ],
          "isUnique": false,
          "concurrently": false,
          "method": "btree",
          "with": {}
        }
      },
      "foreignKeys": {
        "review_cycles_created_by_users_id_fk": {
          "name": "review_cycles_created_by_users_id_fk",
          "tableFrom": "review_cycles",
          "tableTo": "users",
          "columnsFrom": [
            "created_by"
          ],
          "columnsTo": [
            "id"
          ],
          "onDelete": "no action",
          "onUpdate": "no action"
        }
      },
      "compositePrimaryKeys": {},
      "uniqueConstraints": {},
      "policies": {},
      "checkConstraints": {},
      "isRLSEnabled": false
    },
    "public.review_participants": {
      "name": "review_participants",
      "schema": "",
      "columns": {
        "id": {
          "name": "id",
          "type": "serial",
          "primaryKey": true,
          "notNull": true
        },
        "cycle_id": {
          "name": "cycle_id",
          "type": "integer",
          "primaryKey": false,
          "notNull": true
        },
        "employee_id": {
          "name": "employee_id",
          "type": "integer",
          "primaryKey": false,
          "notNull": true
        },
        "manager_employee_id": {
          "name": "manager_employee_id",
          "type": "integer",
          "primaryKey": false,
          "notNull": false
        },
        "status": {
          "name": "status",
          "type": "text",
          "primaryKey": false,
          "notNull": true,
          "default": "'not_started'"
        },
        "submitted_at": {
          "name": "submitted_at",
          "type": "timestamp",
          "primaryKey": false,
          "notNull": false
        },
        "overall_rating": {
          "name": "overall_rating",
          "type": "integer",
          "primaryKey": false,
          "notNull": false
        },
        "created_at": {
          "name": "created_at",
          "type": "timestamp",
          "primaryKey": false,
          "notNull": true,
          "default": "now()"
        },
        "updated_at": {
          "name": "updated_at",
          "type": "timestamp",
          "primaryKey": false,
          "notNull": true,
          "default": "now()"
        }
      },
      "indexes": {
        "review_participants_unique_idx": {
          "name": "review_participants_unique_idx",
          "columns": [
            {
              "expression": "cycle_id",
              "isExpression": false,
              "asc": true,
              "nulls": "last"
            },
            {
              "expression": "employee_id",
              "isExpression": false,
              "asc": true,
              "nulls": "last"
            }
          ],
          "isUnique": true,
          "concurrently": false,
          "method": "btree",
          "with": {}
        },
        "review_participants_cycle_idx": {
          "name": "review_participants_cycle_idx",
          "columns": [
            {
              "expression": "cycle_id",
              "isExpression": false,
              "asc": true,
              "nulls": "last"
            }
          ],
          "isUnique": false,
          "concurrently": false,
          "method": "btree",
          "with": {}
        },
        "review_participants_employee_idx": {
          "name": "review_participants_employee_idx",
          "columns": [
            {
              "expression": "employee_id",
              "isExpression": false,
              "asc": true,
              "nulls": "last"
            }
          ],
          "isUnique": false,
          "concurrently": false,
          "method": "btree",
          "with": {}
        },
        "review_participants_manager_idx": {
          "name": "review_participants_manager_idx",
          "columns": [
            {
              "expression": "manager_employee_id",
              "isExpression": false,
              "asc": true,
              "nulls": "last"
            }
          ],
          "isUnique": false,
          "concurrently": false,
          "method": "btree",
          "with": {}
        },
        "review_participants_status_idx": {
          "name": "review_participants_status_idx",
          "columns": [
            {
              "expression": "status",
              "isExpression": false,
              "asc": true,
              "nulls": "last"
            }
          ],
          "isUnique": false,
          "concurrently": false,
          "method": "btree",
          "with": {}
        }
      },
      "foreignKeys": {
        "review_participants_cycle_id_review_cycles_id_fk": {
          "name": "review_participants_cycle_id_review_cycles_id_fk",
          "tableFrom": "review_participants",
          "tableTo": "review_cycles",
          "columnsFrom": [
            "cycle_id"
          ],
          "columnsTo": [
            "id"
          ],
          "onDelete": "cascade",
          "onUpdate": "no action"
        },
        "review_participants_employee_id_employees_id_fk": {
          "name": "review_participants_employee_id_employees_id_fk",
          "tableFrom": "review_participants",
          "tableTo": "employees",
          "columnsFrom": [
            "employee_id"
          ],
          "columnsTo": [
            "id"
          ],
          "onDelete": "cascade",
          "onUpdate": "no action"
        },
        "review_participants_manager_employee_id_employees_id_fk": {
          "name": "review_participants_manager_employee_id_employees_id_fk",
          "tableFrom": "review_participants",
          "tableTo": "employees",
          "columnsFrom": [
            "manager_employee_id"
          ],
          "columnsTo": [
            "id"
          ],
          "onDelete": "set null",
          "onUpdate": "no action"
        }
      },
      "compositePrimaryKeys": {},
      "uniqueConstraints": {},
      "policies": {},
      "checkConstraints": {},
      "isRLSEnabled": false
    },
    "public.review_responses": {
      "name": "review_responses",
      "schema": "",
      "columns": {
        "id": {
          "name": "id",
          "type": "serial",
          "primaryKey": true,
          "notNull": true
        },
        "participant_id": {
          "name": "participant_id",
          "type": "integer",
          "primaryKey": false,
          "notNull": true
        },
        "responder_employee_id": {
          "name": "responder_employee_id",
          "type": "integer",
          "primaryKey": false,
          "notNull": false
        },
        "responder_type": {
          "name": "responder_type",
          "type": "text",
          "primaryKey": false,
          "notNull": true
        },
        "section_key": {
          "name": "section_key",
          "type": "text",
          "primaryKey": false,
          "notNull": true
        },
        "response": {
          "name": "response",
          "type": "jsonb",
          "primaryKey": false,
          "notNull": false
        },
        "rating": {
          "name": "rating",
          "type": "integer",
          "primaryKey": false,
          "notNull": false
        },
        "created_at": {
          "name": "created_at",
          "type": "timestamp",
          "primaryKey": false,
          "notNull": true,
          "default": "now()"
        },
        "updated_at": {
          "name": "updated_at",
          "type": "timestamp",
          "primaryKey": false,
          "notNull": true,
          "default": "now()"
        }
      },
      "indexes": {
        "review_responses_participant_idx": {
          "name": "review_responses_participant_idx",
          "columns": [
            {
              "expression": "participant_id",
              "isExpression": false,
              "asc": true,
              "nulls": "last"
            }
          ],
          "isUnique": false,
          "concurrently": false,
          "method": "btree",
          "with": {}
        },
        "review_responses_responder_idx": {
          "name": "review_responses_responder_idx",
          "columns": [
            {
              "expression": "responder_employee_id",
              "isExpression": false,
              "asc": true,
              "nulls": "last"
            }
          ],
          "isUnique": false,
          "concurrently": false,
          "method": "btree",
          "with": {}
        },
        "review_responses_type_idx": {
          "name": "review_responses_type_idx",
          "columns": [
            {
              "expression": "responder_type",
              "isExpression": false,
              "asc": true,
              "nulls": "last"
            }
          ],
          "isUnique": false,
          "concurrently": false,
          "method": "btree",
          "with": {}
        }
      },
      "foreignKeys": {
        "review_responses_participant_id_review_participants_id_fk": {
          "name": "review_responses_participant_id_review_participants_id_fk",
          "tableFrom": "review_responses",
          "tableTo": "review_participants",
          "columnsFrom": [
            "participant_id"
          ],
          "columnsTo": [
            "id"
          ],
          "onDelete": "cascade",
          "onUpdate": "no action"
        },
        "review_responses_responder_employee_id_employees_id_fk": {
          "name": "review_responses_responder_employee_id_employees_id_fk",
          "tableFrom": "review_responses",
          "tableTo": "employees",
          "columnsFrom": [
            "responder_employee_id"
          ],
          "columnsTo": [
            "id"
          ],
          "onDelete": "set null",
          "onUpdate": "no action"
        }
      },
      "compositePrimaryKeys": {},
      "uniqueConstraints": {},
      "policies": {},
      "checkConstraints": {},
      "isRLSEnabled": false
    },
    "public.user_departments": {
      "name": "user_departments",
      "schema": "",
      "columns": {
        "id": {
          "name": "id",
          "type": "serial",
          "primaryKey": true,
          "notNull": true
        },
        "user_id": {
          "name": "user_id",
          "type": "varchar(36)",
          "primaryKey": false,
          "notNull": true
        },
        "department_id": {
          "name": "department_id",
          "type": "varchar(50)",
          "primaryKey": false,
          "notNull": true
        },
        "created_at": {
          "name": "created_at",
          "type": "timestamp",
          "primaryKey": false,
          "notNull": true,
          "default": "now()"
        }
      },
      "indexes": {
        "user_departments_unique_idx": {
          "name": "user_departments_unique_idx",
          "columns": [
            {
              "expression": "user_id",
              "isExpression": false,
              "asc": true,
              "nulls": "last"
            },
            {
              "expression": "department_id",
              "isExpression": false,
              "asc": true,
              "nulls": "last"
            }
          ],
          "isUnique": true,
          "concurrently": false,
          "method": "btree",
          "with": {}
        },
        "user_departments_user_idx": {
          "name": "user_departments_user_idx",
          "columns": [
            {
              "expression": "user_id",
              "isExpression": false,
              "asc": true,
              "nulls": "last"
            }
          ],
          "isUnique": false,
          "concurrently": false,
          "method": "btree",
          "with": {}
        },
        "user_departments_dept_idx": {
          "name": "user_departments_dept_idx",
          "columns": [
            {
              "expression": "department_id",
              "isExpression": false,
              "asc": true,
              "nulls": "last"
            }
          ],
          "isUnique": false,
          "concurrently": false,
          "method": "btree",
          "with": {}
        }
      },
      "foreignKeys": {
        "user_departments_user_id_users_id_fk": {
          "name": "user_departments_user_id_users_id_fk",
          "tableFrom": "user_departments",
          "tableTo": "users",
          "columnsFrom": [
            "user_id"
          ],
          "columnsTo": [
            "id"
          ],
          "onDelete": "cascade",
          "onUpdate": "no action"
        }
      },
      "compositePrimaryKeys": {},
      "uniqueConstraints": {},
      "policies": {},
      "checkConstraints": {},
      "isRLSEnabled": false
    },
    "public.users": {
      "name": "users",
      "schema": "",
      "columns": {
        "id": {
          "name": "id",
          "type": "varchar(36)",
          "primaryKey": true,
          "notNull": true,
          "default": "gen_random_uuid()"
        },
        "email": {
          "name": "email",
          "type": "text",
          "primaryKey": false,
          "notNull": true
        },
        "password_hash": {
          "name": "password_hash",
          "type": "text",
          "primaryKey": false,
          "notNull": true
        },
        "first_name": {
          "name": "first_name",
          "type": "text",
          "primaryKey": false,
          "notNull": true
        },
        "last_name": {
          "name": "last_name",
          "type": "text",
          "primaryKey": false,
          "notNull": true
        },
        "role": {
          "name": "role",
          "type": "text",
          "primaryKey": false,
          "notNull": true,
          "default": "'member'"
        },
        "designation": {
          "name": "designation",
          "type": "text",
          "primaryKey": false,
          "notNull": false
        },
        "is_active": {
          "name": "is_active",
          "type": "boolean",
          "primaryKey": false,
          "notNull": true,
          "default": true
        },
        "created_at": {
          "name": "created_at",
          "type": "timestamp",
          "primaryKey": false,
          "notNull": true,
          "default": "now()"
        },
        "updated_at": {
          "name": "updated_at",
          "type": "timestamp",
          "primaryKey": false,
          "notNull": true,
          "default": "now()"
        }
      },
      "indexes": {
        "users_email_idx": {
          "name": "users_email_idx",
          "columns": [
            {
              "expression": "email",
              "isExpression": false,
              "asc": true,
              "nulls": "last"
            }
          ],
          "isUnique": false,
          "concurrently": false,
          "method": "btree",
          "with": {}
        },
        "users_role_idx": {
          "name": "users_role_idx",
          "columns": [
            {
              "expression": "role",
              "isExpression": false,
              "asc": true,
              "nulls": "last"
            }
          ],
          "isUnique": false,
          "concurrently": false,
          "method": "btree",
          "with": {}
        },
        "users_is_active_idx": {
          "name": "users_is_active_idx",
          "columns": [
            {
              "expression": "is_active",
              "isExpression": false,
              "asc": true,
              "nulls": "last"
            }
          ],
          "isUnique": false,
          "concurrently": false,
          "method": "btree",
          "with": {}
        }
      },
      "foreignKeys": {},
      "compositePrimaryKeys": {},
      "uniqueConstraints": {
        "users_email_unique": {
          "name": "users_email_unique",
          "nullsNotDistinct": false,
          "columns": [
            "email"
          ]
        }
      },
      "policies": {},
      "checkConstraints": {},
      "isRLSEnabled": false
    }
  },
  "enums": {},
  "schemas": {},
  "sequences": {},
  "roles": {},
  "policies": {},
  "views": {},
  "_meta": {
    "columns": {},
    "schemas": {},
    "tables": {}
  }
}